<?xml version="1.0"?>
<!-- OSNMA v1.1 (date 05/07/2018) !-->
<masks adkd="0" >
	<sysmask system="gal-e1b" cycle="30" >
	  <bitmask toaL1="25" toaL1L5="5">
		<block  id="1" aidx="03">00000000 11111111 11111111 11111111 11111111 11111111 11111111  11111111 11111111 11111111 11111111 11111111 11111111 11111111 11000000</block> <!-- WT2 (1/2)  00FFFFFFFFFFFF FFFFFFFFFFFFFFC0-->
		<block  id="2" aidx="04">00111111 11111111 00000000 00000000 00000000 00000000 00000000  00000000 00000000 00000000 00000000 00000000 00000000 00000000 00000000</block> <!-- WT2 (2/2)  3FFF0000000000 0000000000000000-->
		<block  id="3" aidx="07">00000000 11111111 11111111 11111111 11111111 11111111 11111111  11111111 11111111 11111111 11111111 11111111 11111111 11111111 11000000</block> <!-- WT4 (1/2)  00FFFFFFFFFFFF FFFFFFFFFFFFFFC0-->
		<block  id="4" aidx="08">00111111 11111111 00000000 00000000 00000000 00000000 00000000  00000000 00000000 00000000 00000000 00000000 00000000 00000000 00000000</block> <!-- WT4 (2/2)  3FFF0000000000 0000000000000000-->
		<block  id="5" aidx="11">00000000 00000000 00000000 00000000 00000000 00000000 00000000  00000000 00000000 00000000 00000000 00000000 00000000 00000000 00000000</block> <!-- WT6 (1/2)-->
		<block  id="6" aidx="12">00000000 00000000 00000000 00000000 00000000 00000000 00000000  00000000 00000000 00000000 00000000 00000000 00000000 00000000 00000000</block> <!-- WT6 (2/2)-->
		<block  id="7" aidx="00">00000000 00000000 00000000 00000000 00000000 00000000 00000000  00000000 00000000 00000000 00000000 00000000 00000000 00000000 00000000</block> <!-- WT7/9 (1/2)-->
		<block  id="8" aidx="00">00000000 00000000 00000000 00000000 00000000 00000000 00000000  00000000 00000000 00000000 00000000 00000000 00000000 00000000 00000000</block> <!-- WT7/9 (2/2)-->
		<block  id="9" aidx="00">00000000 00000000 00000000 00000000 00000000 00000000 00000000  00000000 00000000 00000000 00000000 00000000 00000000 00000000 00000000</block> <!-- WT8/10 (1/2)-->
		<block id="10" aidx="00">00000000 00000000 00000000 00000000 00000000 00000000 00000000  00000000 00000000 00000000 00000000 00000000 00000000 00000000 00000000</block> <!-- WT8/10 (2/2)-->
		<block id="11" aidx="00">00000000 00000000 00000000 00000000 00000000 00000000 00000000  00000000 00000000 00000000 00000000 00000000 00000000 00000000 00000000</block>
		<block id="12" aidx="00">00000000 00000000 00000000 00000000 00000000 00000000 00000000  00000000 00000000 00000000 00000000 00000000 00000000 00000000 00000000</block>
		<block id="13" aidx="00">00000000 00000000 00000000 00000000 00000000 00000000 00000000  00000000 00000000 00000000 00000000 00000000 00000000 00000000 00000000</block>
		<block id="14" aidx="00">00000000 00000000 00000000 00000000 00000000 00000000 00000000  00000000 00000000 00000000 00000000 00000000 00000000 00000000 00000000</block>
		<block id="15" aidx="00">00000000 00000000 00000000 00000000 00000000 00000000 00000000  00000000 00000000 00000000 00000000 00000000 00000000 00000000 00000000</block>
		<block id="16" aidx="00">00000000 00000000 00000000 00000000 00000000 00000000 00000000  00000000 00000000 00000000 00000000 00000000 00000000 00000000 00000000</block>
		<block id="17" aidx="00">00000000 00000000 00000000 00000000 00000000 00000000 00000000  00000000 00000000 00000000 00000000 00000000 00000000 00000000 00000000</block>
		<block id="18" aidx="00">00000000 00000000 00000000 00000000 00000000 00000000 00000000  00000000 00000000 00000000 00000000 00000000 00000000 00000000 00000000</block>
		<block id="19" aidx="00">00000000 00000000 00000000 00000000 00000000 00000000 00000000  00000000 00000000 00000000 00000000 00000000 00000000 00000000 00000000</block>
		<block id="20" aidx="00">00000000 00000000 00000000 00000000 00000000 00000000 00000000  00000000 00000000 00000000 00000000 00000000 00000000 00000000 00000000</block>		
		<block id="21" aidx="01">00000000 11111111 11111111 11111111 11111111 11111111 11111111  11111111 11111111 11111111 11111111 11111111 11111111 11111111 11000000</block> <!-- WT1 (1/2)   00FFFFFFFFFFFF FFFFFFFFFFFFFFC0-->
		<block id="22" aidx="02">00111111 11111111 00000000 00000000 00000000 00000000 00000000  00000000 00000000 00000000 00000000 00000000 00000000 00000000 00000000</block> <!-- WT1 (2/2)   3FFF0000000000 0000000000000000-->
		<block id="23" aidx="05">00000000 11111111 11111111 11111111 11111111 11111111 11111111  11111111 11111111 11111111 11111111 11111111 11111111 11111111 11000000</block> <!-- WT3 (1/2)   00FFFFFFFFFFFF FFFFFFFFFFFFFFC0-->
		<block id="24" aidx="06">00111111 11111111 11000000 00000000 00000000 00000000 00000000  00000000 00000000 00000000 00000000 00000000 00000000 00000000 00000000</block> <!-- WT3 (2/2)   3FFFC000000000 0000000000000000-->		
		<block id="25" aidx="09">00000000 11111111 11111111 11111111 11111111 11111111 11111111  11111111 11111111 11100000 00000000 00000000 00000000 00000000 00000000</block> <!-- WT5 (1/2)	  00FFFFFFFFFFFF FFFFE00000000000-->
		<block id="26" aidx="10">00000000 00000000 00000000 00000000 00000000 00000000 00000000  00000000 00000000 00000000 00000000 00000000 00000000 00000000 00000000</block> <!-- WT5 (2/2)   00000000000000 0000000000000000-->
		<block id="27" aidx="00">00000000 00000000 00000000 00000000 00000000 00000000 00000000  00000000 00000000 00000000 00000000 00000000 00000000 00000000 00000000</block>
		<block id="28" aidx="00">00000000 00000000 00000000 00000000 00000000 00000000 00000000  00000000 00000000 00000000 00000000 00000000 00000000 00000000 00000000</block>
		<block id="29" aidx="00">00000000 00000000 00000000 00000000 00000000 00000000 00000000  00000000 00000000 00000000 00000000 00000000 00000000 00000000 00000000</block>
		<block id="30" aidx="00">00000000 00000000 00000000 00000000 00000000 00000000 00000000  00000000 00000000 00000000 00000000 00000000 00000000 00000000 00000000</block>
	  </bitmask>
	</sysmask>
  
	<sysmask system="gps-l1ca" cycle="30" >
	  <bitmask toaL1="18">
		<block id="1">000000000000000000000000XXXXXX 000000000000000000000000XXXXXX 000000000000111111111111XXXXXX 000000000000000000000000XXXXXX 000000000000000000000000XXXXXX 000000000000000000000000XXXXXX 000000000000000011111111XXXXXX 111111111111111111111111XXXXXX 111111111111111111111111XXXXXX 111111111111111111111100XXXXXX</block> <!-- SF1   !-->
		<block id="2">000000000000000000000000XXXXXX 000000000000000000000000XXXXXX 111111111111111111111111XXXXXX 111111111111111111111111XXXXXX 111111111111111111111111XXXXXX 111111111111111111111111XXXXXX 111111111111111111111111XXXXXX 111111111111111111111111XXXXXX 111111111111111111111111XXXXXX 111111111111111111111100XXXXXX</block>
		<block id="3">000000000000000000000000XXXXXX 000000000000000000000000XXXXXX 111111111111111111111111XXXXXX 111111111111111111111111XXXXXX 111111111111111111111111XXXXXX 111111111111111111111111XXXXXX 111111111111111111111111XXXXXX 111111111111111111111111XXXXXX 111111111111111111111111XXXXXX 111111111111111111111100XXXXXX</block>
		<block id="4" blanking="1" />
		<block id="5" blanking="1" />
	  </bitmask>
	</sysmask>
</masks>
